faassupervisor/__init__.py
faassupervisor/exceptions.py
faassupervisor/logger.py
faassupervisor/supervisor.py
faassupervisor/utils.py
faassupervisor/version.py
faassupervisor/events/__init__.py
faassupervisor/events/apigateway.py
faassupervisor/events/dCache.py
faassupervisor/events/minio.py
faassupervisor/events/onedata.py
faassupervisor/events/s3.py
faassupervisor/events/unknown.py
faassupervisor/faas/__init__.py
faassupervisor/faas/aws_lambda/batch.py
faassupervisor/faas/aws_lambda/container.py
faassupervisor/faas/aws_lambda/function.py
faassupervisor/faas/aws_lambda/function_handler.py
faassupervisor/faas/aws_lambda/supervisor.py
faassupervisor/faas/aws_lambda/udocker.py
faassupervisor/faas/binary/supervisor.py
faassupervisor/storage/__init__.py
faassupervisor/storage/config.py
faassupervisor/storage/providers/__init__.py
faassupervisor/storage/providers/local.py
faassupervisor/storage/providers/minio.py
faassupervisor/storage/providers/onedata.py
faassupervisor/storage/providers/s3.py
faassupervisor/storage/providers/webdav.py
test/unit/__init__.py
test/unit/faassupervisor/events.py
test/unit/faassupervisor/faas.py
test/unit/faassupervisor/storage.py
test/unit/faassupervisor/utils.py
faas_supervisor-1.5.8.dist-info/LICENSE
faas_supervisor-1.5.8.dist-info/METADATA
faas_supervisor-1.5.8.dist-info/WHEEL
faas_supervisor-1.5.8.dist-info/top_level.txt
faas_supervisor-1.5.8.dist-info/RECORD
