Metadata-Version: 2.1
Name: faas-supervisor
Version: 1.5.8
Summary: Input/Output data manager for FaaS
Home-page: https://github.com/grycap/faas-supervisor
Author: GRyCAP - Universitat Politecnica de Valencia
Author-email: alpegon3@upv.es
License: Apache 2.0
Platform: UNKNOWN
Classifier: Programming Language :: Python :: 3
Classifier: License :: OSI Approved :: Apache Software License
Requires-Dist: webdavclient3 (==3.14.6requests)
Requires-Dist: boto3
Requires-Dist: setuptools (>=40.8.0)
Requires-Dist: pyyaml
